takumi_sqlalchemy/__init__.py
takumi_sqlalchemy/database.py
takumi_sqlalchemy/hook.py
takumi_sqlalchemy/routing.py
takumi_sqlalchemy/utils.py
takumi_sqlalchemy-0.1.5.dist-info/DESCRIPTION.rst
takumi_sqlalchemy-0.1.5.dist-info/METADATA
takumi_sqlalchemy-0.1.5.dist-info/metadata.json
takumi_sqlalchemy-0.1.5.dist-info/RECORD
takumi_sqlalchemy-0.1.5.dist-info/top_level.txt
takumi_sqlalchemy-0.1.5.dist-info/WHEEL
