Metadata-Version: 2.0
Name: takumi-sqlalchemy
Version: 0.1.5
Summary: Sqlalchemy utilities for Takumi
Home-page: https://github.com/elemepi/takumi-sqlalchemy
Author: Eleme Lab
Author-email: imaralla@icloud.com
License: UNKNOWN
Platform: UNKNOWN
Requires-Dist: takumi
Requires-Dist: takumi-config
Requires-Dist: sqlalchemy
